[
  {
    "id":1,
    "title":"첫번째 글입니다.",
    "content":"첫번째 글의 내용입니다.",
    "comments" : [
      {
        "id" : 11,
        "content":"댓글1"
      },
      {
        "id" : 22,
        "content":"댓글2"
      },
      {
        "id" : 33,
        "content":"댓글3"
      },
      {
        "id" : 44,
        "content":"댓글4"
      }
    ]
    
  },
  {
    "id":2,
    "title":"두번째 글입니다.",
    "content":"두번째 글의 내용입니다.",
    "comments" : [
      {
        "id" : 11,
        "content":"댓글11"
      },
      {
        "id" : 22,
        "content":"댓글22"
      },
      {
        "id" : 33,
        "content":"댓글33"
      },
      {
        "id" : 44,
        "content":"댓글44"
      }
    ]
    
  },
  {
    "id":3,
    "title":"새번째 글입니다.",
    "content":"세번째 글의 내용입니다.",
    "comments" : [
      {
        "id" : 11,
        "content":"댓글111"
      },
      {
        "id" : 22,
        "content":"댓글222"
      },
      {
        "id" : 33,
        "content":"댓글333"
      }
    ]
    
  }
]